voyado/__init__.py
voyado/base.py
voyado/client.py
voyado/contacts.py
voyado/exceptions.py
voyado/orders.py
voyado/points.py
voyado/promotions.py
voyado/transactions.py
voyado/utils.py
voyado/vouchers.py
voyado_engage-0.1.0.dist-info/licenses/LICENSE
voyado_engage-0.1.0.dist-info/METADATA
voyado_engage-0.1.0.dist-info/WHEEL
voyado_engage-0.1.0.dist-info/top_level.txt
voyado_engage-0.1.0.dist-info/RECORD
